visualqe/__init__.py
visualqe/cli.py
visualqe/core.py
visualqe/exceptions.py
visualqe/models.py
visualqe/pytest_plugin.py
visualqe/analysis/__init__.py
visualqe/analysis/base.py
visualqe/analysis/gemini.py
visualqe/analysis/prompts.py
visualqe/baseline/__init__.py
visualqe/baseline/base.py
visualqe/baseline/local.py
visualqe/capture/__init__.py
visualqe/capture/base.py
visualqe/capture/pixcap.py
visualqe/diff/__init__.py
visualqe/diff/base.py
visualqe/diff/pixel.py
visualqe/diff/ssim.py
visualqe/reporting/__init__.py
visualqe/reporting/html.py
visualqe/reporting/json.py
visualqe-0.1.1.dist-info/METADATA
visualqe-0.1.1.dist-info/WHEEL
visualqe-0.1.1.dist-info/entry_points.txt
visualqe-0.1.1.dist-info/licenses/LICENSE
visualqe-0.1.1.dist-info/RECORD
