Metadata-Version: 2.4
Name: visualqe
Version: 0.1.1
Summary: Visual regression testing with LLM-powered semantic analysis
Project-URL: Homepage, https://github.com/dan-shah/regression_test_visual
Project-URL: Repository, https://github.com/dan-shah/regression_test_visual
Project-URL: Documentation, https://github.com/dan-shah/regression_test_visual#readme
Project-URL: Issues, https://github.com/dan-shah/regression_test_visual/issues
Author: Dan Shah
License-Expression: MIT
License-File: LICENSE
Keywords: gemini,llm,qa,screenshot,testing,visual-regression
Classifier: Development Status :: 3 - Alpha
Classifier: Intended Audience :: Developers
Classifier: License :: OSI Approved :: MIT License
Classifier: Programming Language :: Python :: 3.9
Classifier: Programming Language :: Python :: 3.10
Classifier: Programming Language :: Python :: 3.11
Classifier: Programming Language :: Python :: 3.12
Classifier: Topic :: Software Development :: Quality Assurance
Classifier: Topic :: Software Development :: Testing
Requires-Python: >=3.9
Requires-Dist: google-generativeai>=0.3.0
Requires-Dist: pillow>=9.0.0
Requires-Dist: pydantic>=2.0.0
Requires-Dist: requests>=2.28.0
Requires-Dist: scikit-image>=0.20.0
Provides-Extra: dev
Requires-Dist: mypy>=1.0.0; extra == 'dev'
Requires-Dist: pytest-cov>=4.0.0; extra == 'dev'
Requires-Dist: pytest>=7.0.0; extra == 'dev'
Requires-Dist: ruff>=0.1.0; extra == 'dev'
Requires-Dist: types-pillow>=9.0.0; extra == 'dev'
Requires-Dist: types-requests>=2.28.0; extra == 'dev'
Provides-Extra: pytest
Requires-Dist: pytest>=7.0.0; extra == 'pytest'
